pierpy/sqlserv_tools.py
pierpy-0.3.0.7.dist-info/LICENSE
pierpy-0.3.0.7.dist-info/METADATA
pierpy-0.3.0.7.dist-info/WHEEL
pierpy-0.3.0.7.dist-info/top_level.txt
pierpy-0.3.0.7.dist-info/RECORD
