Metadata-Version: 2.1
Name: pierpy
Version: 0.3.0.7
Summary: A python package for internally use in PIER
Home-page: https://github.com/surasakcho/pierpy
Author: Surasak Choedpasuporn
Author-email: surasakc@bot.or.th
License: UNKNOWN
Platform: UNKNOWN
Classifier: Programming Language :: Python :: 3
Classifier: License :: OSI Approved :: MIT License
Classifier: Operating System :: OS Independent
Requires-Python: >=3.6.1,<4.0.0
License-File: LICENSE
Requires-Dist: sqlalchemy
